transforms84/__init__.py
transforms84/definitions.py
transforms84/distances.cp312-win_amd64.pyd
transforms84/distances.pyi
transforms84/helpers.cp312-win_amd64.pyd
transforms84/helpers.pyi
transforms84/py.typed
transforms84/systems.py
transforms84/transforms.cp312-win_amd64.pyd
transforms84/transforms.pyi
transforms84-1.2.1.dist-info/licenses/LICENSE.txt
transforms84-1.2.1.dist-info/METADATA
transforms84-1.2.1.dist-info/WHEEL
transforms84-1.2.1.dist-info/top_level.txt
transforms84-1.2.1.dist-info/RECORD
