Metadata-Version: 2.4
Name: transforms84
Version: 1.2.1
Summary: Geographic system transformations with helper functions
Author-email: Daniel Stoops <google@gmail.com>
License: BSD-3-Clause license
Project-URL: Homepage, https://github.com/Stoops-ML/transforms84
Project-URL: Repository, https://github.com/Stoops-ML/transforms84
Project-URL: Issues, https://github.com/Stoops-ML/transforms84/issues
Classifier: Intended Audience :: Education
Classifier: Intended Audience :: Science/Research
Classifier: Programming Language :: Python
Classifier: Programming Language :: Python :: 3
Classifier: Programming Language :: Python :: 3.9
Classifier: Programming Language :: Python :: 3.10
Classifier: Programming Language :: Python :: 3.11
Classifier: Programming Language :: Python :: 3.12
Classifier: Programming Language :: Python :: 3.13
Classifier: Programming Language :: Python :: Implementation :: CPython
Classifier: Topic :: Scientific/Engineering
Requires-Python: >=3.9
License-File: LICENSE.txt
Requires-Dist: numpy<3.0.0,>=1.0.0
Provides-Extra: dev
Requires-Dist: ruff>=0.9.7; extra == "dev"
Requires-Dist: pytest>=8.3.2; extra == "dev"
Requires-Dist: pytest-cov>=5.0.0; extra == "dev"
Requires-Dist: mypy>=1.11.1; extra == "dev"
Requires-Dist: tox>=4.17.1; extra == "dev"
Requires-Dist: wheel>=0.44.0; extra == "dev"
Requires-Dist: setuptools>=72.2.0; extra == "dev"
Requires-Dist: setuptools-scm; extra == "dev"
Requires-Dist: build>=1.2.1; extra == "dev"
Requires-Dist: pandas>=2.0.0; extra == "dev"
Requires-Dist: pandas-stubs>=2.0.0; extra == "dev"
Provides-Extra: examples
Requires-Dist: jupyterlab>=4.2.4; extra == "examples"
Requires-Dist: shapely>=2.0.5; extra == "examples"
Requires-Dist: czml3<3; extra == "examples"
Requires-Dist: pandas>=2.0.0; extra == "examples"
Dynamic: license-file
